{
  "@context": [
    "http://iiif.io/api/extension/navplace/context.json",
    "http://iiif.io/api/presentation/3/context.json"
  ],
  "id": "https://amsterdamtimemachine.github.io/amsterdam-in-motion-750/iiif/demonstratie-stichting-jaccuse.json",
  "type": "Manifest",
  "label": {
    "nl": [
      "Demonstratie stichting J'Accuse"
    ]
  },
  "metadata": [
    {
      "label": {
        "nl": [
          "Datum (begin)"
        ]
      },
      "value": {
        "nl": [
          "1969-05-04"
        ]
      }
    },
    {
      "label": {
        "nl": [
          "Datum (eind)"
        ]
      },
      "value": {
        "nl": [
          "1969-05-04"
        ]
      }
    },
    {
      "label": {
        "nl": [
          "Locatie's"
        ]
      },
      "value": {
        "nl": [
          ""
        ]
      }
    },
    {
      "label": {
        "nl": [
          "Classificatie's"
        ]
      },
      "value": {
        "nl": [
          "Demonstraties, Binnenlandse politiek"
        ]
      }
    },
    {
      "label": {
        "nl": [
          "Classificatie's (URI)"
        ]
      },
      "value": {
        "nl": [
          "https://digitaalerfgoed.poolparty.biz/atm/42d4c3eb-08e3-4b9a-8c8a-a124ae114bab, https://digitaalerfgoed.poolparty.biz/atm/f9ee5edc-2fb1-48fa-a4e6-d34cb38913c3"
        ]
      }
    }
  ],
  "summary": {},
  "items": [
    {
      "id": "https://amsterdamtimemachine.github.io/amsterdam-in-motion-750/iiif/demonstratie-stichting-jaccuse/p1/canvas/828",
      "type": "Canvas",
      "label": {},
      "height": 2413,
      "width": 3579,
      "metadata": [
        {
          "label": {
            "nl": [
              "Naam"
            ]
          },
          "value": {
            "nl": [
              ""
            ]
          }
        },
        {
          "label": {
            "nl": [
              "Beschrijving"
            ]
          },
          "value": {
            "nl": [
              "De Stichting JAccuse hield demonstratieve bijeenkomst in Kras, Amsterdam overzicht"
            ]
          }
        },
        {
          "label": {
            "nl": [
              "Datum (begin)"
            ]
          },
          "value": {
            "nl": [
              "1969-05-04"
            ]
          }
        },
        {
          "label": {
            "nl": [
              "Datum (eind)"
            ]
          },
          "value": {
            "nl": [
              "1969-05-04"
            ]
          }
        },
        {
          "label": {
            "nl": [
              "Fotograaf"
            ]
          },
          "value": {
            "nl": [
              "Mieremet, Rob / Anefo"
            ]
          }
        },
        {
          "label": {
            "nl": [
              "Archief"
            ]
          },
          "value": {
            "nl": [
              "Nationaal Archief"
            ]
          }
        },
        {
          "label": {
            "nl": [
              "URL"
            ]
          },
          "value": {
            "nl": [
              "http://hdl.handle.net/10648/ab67e1c6-d0b4-102d-bcf8-003048976d84"
            ]
          }
        },
        {
          "label": {
            "nl": [
              "Locatie"
            ]
          },
          "value": {
            "nl": [
              ""
            ]
          }
        }
      ],
      "items": [
        {
          "id": "https://amsterdamtimemachine.github.io/amsterdam-in-motion-750/iiif/demonstratie-stichting-jaccuse/p1/canvas/828/page",
          "type": "AnnotationPage",
          "items": [
            {
              "id": "https://amsterdamtimemachine.github.io/amsterdam-in-motion-750/iiif/demonstratie-stichting-jaccuse/p1/canvas/828/anno",
              "type": "Annotation",
              "motivation": "painting",
              "body": {
                "id": "https://service.archief.nl/iip/iipsrv?IIIF=/74/2e/ee/3e/86/ca/4f/1a/af/90/d6/54/27/33/31/37/d82ba076-f57f-46cc-8994-dc2c1aadad89.jp2/full/full/0/default.jpg",
                "type": "Image",
                "height": 2413,
                "width": 3579,
                "service": [
                  {
                    "@id": "https://service.archief.nl/iip/iipsrv?IIIF=/74/2e/ee/3e/86/ca/4f/1a/af/90/d6/54/27/33/31/37/d82ba076-f57f-46cc-8994-dc2c1aadad89.jp2",
                    "@type": "ImageService2",
                    "profile": "http://iiif.io/api/image/2/level1"
                  }
                ],
                "format": "image/jpeg"
              },
              "target": "https://amsterdamtimemachine.github.io/amsterdam-in-motion-750/iiif/demonstratie-stichting-jaccuse/p1/canvas/828"
            }
          ]
        }
      ]
    },
    {
      "id": "https://amsterdamtimemachine.github.io/amsterdam-in-motion-750/iiif/demonstratie-stichting-jaccuse/p1/canvas/829",
      "type": "Canvas",
      "label": {},
      "height": 2413,
      "width": 3684,
      "metadata": [
        {
          "label": {
            "nl": [
              "Naam"
            ]
          },
          "value": {
            "nl": [
              ""
            ]
          }
        },
        {
          "label": {
            "nl": [
              "Beschrijving"
            ]
          },
          "value": {
            "nl": [
              "De Stichting JAccuse hield demonstratieve bijeenkomst in Kras, Amsterdam overzicht"
            ]
          }
        },
        {
          "label": {
            "nl": [
              "Datum (begin)"
            ]
          },
          "value": {
            "nl": [
              "1969-05-04"
            ]
          }
        },
        {
          "label": {
            "nl": [
              "Datum (eind)"
            ]
          },
          "value": {
            "nl": [
              "1969-05-04"
            ]
          }
        },
        {
          "label": {
            "nl": [
              "Fotograaf"
            ]
          },
          "value": {
            "nl": [
              "Mieremet, Rob / Anefo"
            ]
          }
        },
        {
          "label": {
            "nl": [
              "Archief"
            ]
          },
          "value": {
            "nl": [
              "Nationaal Archief"
            ]
          }
        },
        {
          "label": {
            "nl": [
              "URL"
            ]
          },
          "value": {
            "nl": [
              "http://hdl.handle.net/10648/ab67e0fe-d0b4-102d-bcf8-003048976d84"
            ]
          }
        },
        {
          "label": {
            "nl": [
              "Locatie"
            ]
          },
          "value": {
            "nl": [
              ""
            ]
          }
        }
      ],
      "items": [
        {
          "id": "https://amsterdamtimemachine.github.io/amsterdam-in-motion-750/iiif/demonstratie-stichting-jaccuse/p1/canvas/829/page",
          "type": "AnnotationPage",
          "items": [
            {
              "id": "https://amsterdamtimemachine.github.io/amsterdam-in-motion-750/iiif/demonstratie-stichting-jaccuse/p1/canvas/829/anno",
              "type": "Annotation",
              "motivation": "painting",
              "body": {
                "id": "https://service.archief.nl/iip/iipsrv?IIIF=/6e/cd/5b/fb/73/33/49/e1/96/26/1e/2f/3e/fa/d7/f0/67876af3-9aa4-42a1-be2f-27032c563ae2.jp2/full/full/0/default.jpg",
                "type": "Image",
                "height": 2413,
                "width": 3684,
                "service": [
                  {
                    "@id": "https://service.archief.nl/iip/iipsrv?IIIF=/6e/cd/5b/fb/73/33/49/e1/96/26/1e/2f/3e/fa/d7/f0/67876af3-9aa4-42a1-be2f-27032c563ae2.jp2",
                    "@type": "ImageService2",
                    "profile": "http://iiif.io/api/image/2/level1"
                  }
                ],
                "format": "image/jpeg"
              },
              "target": "https://amsterdamtimemachine.github.io/amsterdam-in-motion-750/iiif/demonstratie-stichting-jaccuse/p1/canvas/829"
            }
          ]
        }
      ]
    },
    {
      "id": "https://amsterdamtimemachine.github.io/amsterdam-in-motion-750/iiif/demonstratie-stichting-jaccuse/p1/canvas/830",
      "type": "Canvas",
      "label": {},
      "height": 3684,
      "width": 2413,
      "metadata": [
        {
          "label": {
            "nl": [
              "Naam"
            ]
          },
          "value": {
            "nl": [
              ""
            ]
          }
        },
        {
          "label": {
            "nl": [
              "Beschrijving"
            ]
          },
          "value": {
            "nl": [
              "De Stichting JAccuse hield demonstratieve bijeenkomst in Kras, Amsterdam overzicht"
            ]
          }
        },
        {
          "label": {
            "nl": [
              "Datum (begin)"
            ]
          },
          "value": {
            "nl": [
              "1969-05-04"
            ]
          }
        },
        {
          "label": {
            "nl": [
              "Datum (eind)"
            ]
          },
          "value": {
            "nl": [
              "1969-05-04"
            ]
          }
        },
        {
          "label": {
            "nl": [
              "Fotograaf"
            ]
          },
          "value": {
            "nl": [
              "Mieremet, Rob / Anefo"
            ]
          }
        },
        {
          "label": {
            "nl": [
              "Archief"
            ]
          },
          "value": {
            "nl": [
              "Nationaal Archief"
            ]
          }
        },
        {
          "label": {
            "nl": [
              "URL"
            ]
          },
          "value": {
            "nl": [
              "http://hdl.handle.net/10648/ab67e00e-d0b4-102d-bcf8-003048976d84"
            ]
          }
        },
        {
          "label": {
            "nl": [
              "Locatie"
            ]
          },
          "value": {
            "nl": [
              ""
            ]
          }
        }
      ],
      "items": [
        {
          "id": "https://amsterdamtimemachine.github.io/amsterdam-in-motion-750/iiif/demonstratie-stichting-jaccuse/p1/canvas/830/page",
          "type": "AnnotationPage",
          "items": [
            {
              "id": "https://amsterdamtimemachine.github.io/amsterdam-in-motion-750/iiif/demonstratie-stichting-jaccuse/p1/canvas/830/anno",
              "type": "Annotation",
              "motivation": "painting",
              "body": {
                "id": "https://service.archief.nl/iip/iipsrv?IIIF=/3e/52/9d/f1/11/b7/41/aa/9a/8e/7d/cd/63/ae/27/3c/7c6cb0bf-c1a0-4d37-887a-e3abcebe8b69.jp2/full/full/0/default.jpg",
                "type": "Image",
                "height": 3684,
                "width": 2413,
                "service": [
                  {
                    "@id": "https://service.archief.nl/iip/iipsrv?IIIF=/3e/52/9d/f1/11/b7/41/aa/9a/8e/7d/cd/63/ae/27/3c/7c6cb0bf-c1a0-4d37-887a-e3abcebe8b69.jp2",
                    "@type": "ImageService2",
                    "profile": "http://iiif.io/api/image/2/level1"
                  }
                ],
                "format": "image/jpeg"
              },
              "target": "https://amsterdamtimemachine.github.io/amsterdam-in-motion-750/iiif/demonstratie-stichting-jaccuse/p1/canvas/830"
            }
          ]
        }
      ]
    },
    {
      "id": "https://amsterdamtimemachine.github.io/amsterdam-in-motion-750/iiif/demonstratie-stichting-jaccuse/p1/canvas/831",
      "type": "Canvas",
      "label": {},
      "height": 2413,
      "width": 3684,
      "metadata": [
        {
          "label": {
            "nl": [
              "Naam"
            ]
          },
          "value": {
            "nl": [
              ""
            ]
          }
        },
        {
          "label": {
            "nl": [
              "Beschrijving"
            ]
          },
          "value": {
            "nl": [
              "De Stichting JAccuse hield demonstratieve bijeenkomst in Kras, Amsterdam prof.dr. J. Verkuijl aan het woord"
            ]
          }
        },
        {
          "label": {
            "nl": [
              "Datum (begin)"
            ]
          },
          "value": {
            "nl": [
              "1969-05-04"
            ]
          }
        },
        {
          "label": {
            "nl": [
              "Datum (eind)"
            ]
          },
          "value": {
            "nl": [
              "1969-05-04"
            ]
          }
        },
        {
          "label": {
            "nl": [
              "Fotograaf"
            ]
          },
          "value": {
            "nl": [
              "Mieremet, Rob / Anefo"
            ]
          }
        },
        {
          "label": {
            "nl": [
              "Archief"
            ]
          },
          "value": {
            "nl": [
              "Nationaal Archief"
            ]
          }
        },
        {
          "label": {
            "nl": [
              "URL"
            ]
          },
          "value": {
            "nl": [
              "http://hdl.handle.net/10648/ab67de74-d0b4-102d-bcf8-003048976d84"
            ]
          }
        },
        {
          "label": {
            "nl": [
              "Locatie"
            ]
          },
          "value": {
            "nl": [
              ""
            ]
          }
        }
      ],
      "items": [
        {
          "id": "https://amsterdamtimemachine.github.io/amsterdam-in-motion-750/iiif/demonstratie-stichting-jaccuse/p1/canvas/831/page",
          "type": "AnnotationPage",
          "items": [
            {
              "id": "https://amsterdamtimemachine.github.io/amsterdam-in-motion-750/iiif/demonstratie-stichting-jaccuse/p1/canvas/831/anno",
              "type": "Annotation",
              "motivation": "painting",
              "body": {
                "id": "https://service.archief.nl/iip/iipsrv?IIIF=/11/9e/13/02/90/18/4d/3c/91/e9/67/9f/e3/5a/62/38/71580896-1783-4573-a3ff-f9d5296f138e.jp2/full/full/0/default.jpg",
                "type": "Image",
                "height": 2413,
                "width": 3684,
                "service": [
                  {
                    "@id": "https://service.archief.nl/iip/iipsrv?IIIF=/11/9e/13/02/90/18/4d/3c/91/e9/67/9f/e3/5a/62/38/71580896-1783-4573-a3ff-f9d5296f138e.jp2",
                    "@type": "ImageService2",
                    "profile": "http://iiif.io/api/image/2/level1"
                  }
                ],
                "format": "image/jpeg"
              },
              "target": "https://amsterdamtimemachine.github.io/amsterdam-in-motion-750/iiif/demonstratie-stichting-jaccuse/p1/canvas/831"
            }
          ]
        }
      ]
    }
  ],
  "seeAlso": [
    {
      "@type": "schema:Event",
      "schema:name": "Demonstratie stichting J'Accuse",
      "schema:description": "",
      "schema:startDate": {
        "@type": "xsd:date",
        "@value": "1969-05-04"
      },
      "schema:endDate": {
        "@type": "xsd:date",
        "@value": "1969-05-04"
      },
      "schema:location": [
        {
          "@type": "schema:Place",
          "schema:name": ""
        }
      ],
      "schema:additionalType": [
        {
          "@id": "https://digitaalerfgoed.poolparty.biz/atm/42d4c3eb-08e3-4b9a-8c8a-a124ae114bab",
          "@type": "skos:Concept",
          "skos:prefLabel": {
            "@language": "nl",
            "@value": "Demonstraties"
          }
        },
        {
          "@id": "https://digitaalerfgoed.poolparty.biz/atm/f9ee5edc-2fb1-48fa-a4e6-d34cb38913c3",
          "@type": "skos:Concept",
          "skos:prefLabel": {
            "@language": "nl",
            "@value": "Binnenlandse politiek"
          }
        }
      ]
    }
  ]
}