{
  "@context": [
    "http://iiif.io/api/extension/navplace/context.json",
    "http://iiif.io/api/presentation/3/context.json"
  ],
  "id": "https://amsterdamtimemachine.github.io/amsterdam-in-motion-750/iiif/kabouters-aktie-tegen-autos-en-uitlaatgassen.json",
  "type": "Manifest",
  "label": {
    "nl": [
      "Kabouters-aktie tegen autos en uitlaatgassen"
    ]
  },
  "metadata": [
    {
      "label": {
        "nl": [
          "Datum (begin)"
        ]
      },
      "value": {
        "nl": [
          "1970-04-07"
        ]
      }
    },
    {
      "label": {
        "nl": [
          "Datum (eind)"
        ]
      },
      "value": {
        "nl": [
          "1970-04-07"
        ]
      }
    },
    {
      "label": {
        "nl": [
          "Locatie's"
        ]
      },
      "value": {
        "nl": [
          ""
        ]
      }
    },
    {
      "label": {
        "nl": [
          "Classificatie's"
        ]
      },
      "value": {
        "nl": [
          "Demonstraties, Klimaat, Mobiliteit"
        ]
      }
    },
    {
      "label": {
        "nl": [
          "Classificatie's (URI)"
        ]
      },
      "value": {
        "nl": [
          "https://digitaalerfgoed.poolparty.biz/atm/42d4c3eb-08e3-4b9a-8c8a-a124ae114bab, https://digitaalerfgoed.poolparty.biz/atm/a3c22faf-7d0a-4476-b6fc-1969d56481a3, https://digitaalerfgoed.poolparty.biz/atm/08f07179-519a-47c2-8f76-3938ac63e53f"
        ]
      }
    }
  ],
  "summary": {},
  "items": [
    {
      "id": "https://amsterdamtimemachine.github.io/amsterdam-in-motion-750/iiif/kabouters-aktie-tegen-autos-en-uitlaatgassen.json/p1/canvas/1018",
      "type": "Canvas",
      "label": {
        "nl": [
          "Leidsestraat 109-99"
        ]
      },
      "height": 2208,
      "width": 2886,
      "metadata": [
        {
          "label": {
            "nl": [
              "Naam"
            ]
          },
          "value": {
            "nl": [
              "Leidsestraat 109-99"
            ]
          }
        },
        {
          "label": {
            "nl": [
              "Beschrijving"
            ]
          },
          "value": {
            "nl": [
              "Kabouterpartij weer actief. De Guerilla-afdeling van de kabouters voerde actie tegen de auto's en de kanker verwekkende uitlaatgassen in de Amsterdamse binnenstad. Gezien vanaf het Leidseplein richting Prinsengracht."
            ]
          }
        },
        {
          "label": {
            "nl": [
              "Datum (begin)"
            ]
          },
          "value": {
            "nl": [
              "1970-04-07"
            ]
          }
        },
        {
          "label": {
            "nl": [
              "Datum (eind)"
            ]
          },
          "value": {
            "nl": [
              "1970-04-07"
            ]
          }
        },
        {
          "label": {
            "nl": [
              "Fotograaf"
            ]
          },
          "value": {
            "nl": [
              ""
            ]
          }
        },
        {
          "label": {
            "nl": [
              "Archief"
            ]
          },
          "value": {
            "nl": [
              "Stadsarchief Amsterdam"
            ]
          }
        },
        {
          "label": {
            "nl": [
              "URL"
            ]
          },
          "value": {
            "nl": [
              "https://archief.amsterdam/beeldbank/detail/064190b7-7603-c004-a094-dcfd1d52caf8"
            ]
          }
        },
        {
          "label": {
            "nl": [
              "Locatie"
            ]
          },
          "value": {
            "nl": [
              ""
            ]
          }
        }
      ],
      "items": [
        {
          "id": "https://amsterdamtimemachine.github.io/amsterdam-in-motion-750/iiif/kabouters-aktie-tegen-autos-en-uitlaatgassen.json/p1/canvas/1018/page",
          "type": "AnnotationPage",
          "items": [
            {
              "id": "https://amsterdamtimemachine.github.io/amsterdam-in-motion-750/iiif/kabouters-aktie-tegen-autos-en-uitlaatgassen.json/p1/canvas/1018/anno",
              "type": "Annotation",
              "motivation": "painting",
              "body": {
                "id": "https://stadsarchiefamsterdam.memorix.io/resources/records/media/064190b7-7603-c004-a094-dcfd1d52caf8/iiif/3/57505814/full/max/0/default.jpg",
                "type": "Image",
                "height": 2208,
                "width": 2886,
                "service": [
                  {
                    "id": "https://stadsarchiefamsterdam.memorix.io/resources/records/media/064190b7-7603-c004-a094-dcfd1d52caf8/iiif/3/57505814",
                    "type": "ImageService3",
                    "profile": "level2"
                  }
                ],
                "format": "image/jpeg"
              },
              "target": "https://amsterdamtimemachine.github.io/amsterdam-in-motion-750/iiif/kabouters-aktie-tegen-autos-en-uitlaatgassen.json/p1/canvas/1018"
            }
          ]
        }
      ]
    },
    {
      "id": "https://amsterdamtimemachine.github.io/amsterdam-in-motion-750/iiif/kabouters-aktie-tegen-autos-en-uitlaatgassen.json/p1/canvas/1019",
      "type": "Canvas",
      "label": {},
      "height": 2425,
      "width": 3682,
      "metadata": [
        {
          "label": {
            "nl": [
              "Naam"
            ]
          },
          "value": {
            "nl": [
              ""
            ]
          }
        },
        {
          "label": {
            "nl": [
              "Beschrijving"
            ]
          },
          "value": {
            "nl": [
              "Kabouters-guerilla-afdeling voert aktie tegen autos en uitlaatgassen in Amsterdam. Leidsestraat met politieagenten"
            ]
          }
        },
        {
          "label": {
            "nl": [
              "Datum (begin)"
            ]
          },
          "value": {
            "nl": [
              "1970-04-07"
            ]
          }
        },
        {
          "label": {
            "nl": [
              "Datum (eind)"
            ]
          },
          "value": {
            "nl": [
              "1970-04-07"
            ]
          }
        },
        {
          "label": {
            "nl": [
              "Fotograaf"
            ]
          },
          "value": {
            "nl": [
              "Verhoeff, Bert / Anefo"
            ]
          }
        },
        {
          "label": {
            "nl": [
              "Archief"
            ]
          },
          "value": {
            "nl": [
              "Nationaal Archief"
            ]
          }
        },
        {
          "label": {
            "nl": [
              "URL"
            ]
          },
          "value": {
            "nl": [
              "http://hdl.handle.net/10648/ab931184-d0b4-102d-bcf8-003048976d84"
            ]
          }
        },
        {
          "label": {
            "nl": [
              "Locatie"
            ]
          },
          "value": {
            "nl": [
              ""
            ]
          }
        }
      ],
      "items": [
        {
          "id": "https://amsterdamtimemachine.github.io/amsterdam-in-motion-750/iiif/kabouters-aktie-tegen-autos-en-uitlaatgassen.json/p1/canvas/1019/page",
          "type": "AnnotationPage",
          "items": [
            {
              "id": "https://amsterdamtimemachine.github.io/amsterdam-in-motion-750/iiif/kabouters-aktie-tegen-autos-en-uitlaatgassen.json/p1/canvas/1019/anno",
              "type": "Annotation",
              "motivation": "painting",
              "body": {
                "id": "https://service.archief.nl/iip/iipsrv?IIIF=/ff/1f/5c/39/bf/6d/44/2d/88/36/83/84/cd/45/a8/c1/3027078d-a4cd-4130-b3f9-be57aabfb37e.jp2/full/full/0/default.jpg",
                "type": "Image",
                "height": 2425,
                "width": 3682,
                "service": [
                  {
                    "@id": "https://service.archief.nl/iip/iipsrv?IIIF=/ff/1f/5c/39/bf/6d/44/2d/88/36/83/84/cd/45/a8/c1/3027078d-a4cd-4130-b3f9-be57aabfb37e.jp2",
                    "@type": "ImageService2",
                    "profile": "http://iiif.io/api/image/2/level1"
                  }
                ],
                "format": "image/jpeg"
              },
              "target": "https://amsterdamtimemachine.github.io/amsterdam-in-motion-750/iiif/kabouters-aktie-tegen-autos-en-uitlaatgassen.json/p1/canvas/1019"
            }
          ]
        }
      ]
    },
    {
      "id": "https://amsterdamtimemachine.github.io/amsterdam-in-motion-750/iiif/kabouters-aktie-tegen-autos-en-uitlaatgassen.json/p1/canvas/1020",
      "type": "Canvas",
      "label": {},
      "height": 2425,
      "width": 3703,
      "metadata": [
        {
          "label": {
            "nl": [
              "Naam"
            ]
          },
          "value": {
            "nl": [
              ""
            ]
          }
        },
        {
          "label": {
            "nl": [
              "Beschrijving"
            ]
          },
          "value": {
            "nl": [
              "Kabouters-guerilla-afdeling voert aktie tegen autos en uitlaatgassen in Amsterdam. Wegversperring in Leidsestraat"
            ]
          }
        },
        {
          "label": {
            "nl": [
              "Datum (begin)"
            ]
          },
          "value": {
            "nl": [
              "1970-04-07"
            ]
          }
        },
        {
          "label": {
            "nl": [
              "Datum (eind)"
            ]
          },
          "value": {
            "nl": [
              "1970-04-07"
            ]
          }
        },
        {
          "label": {
            "nl": [
              "Fotograaf"
            ]
          },
          "value": {
            "nl": [
              "Verhoeff, Bert / Anefo"
            ]
          }
        },
        {
          "label": {
            "nl": [
              "Archief"
            ]
          },
          "value": {
            "nl": [
              "Nationaal Archief"
            ]
          }
        },
        {
          "label": {
            "nl": [
              "URL"
            ]
          },
          "value": {
            "nl": [
              "http://hdl.handle.net/10648/ab930cd4-d0b4-102d-bcf8-003048976d84"
            ]
          }
        },
        {
          "label": {
            "nl": [
              "Locatie"
            ]
          },
          "value": {
            "nl": [
              ""
            ]
          }
        }
      ],
      "items": [
        {
          "id": "https://amsterdamtimemachine.github.io/amsterdam-in-motion-750/iiif/kabouters-aktie-tegen-autos-en-uitlaatgassen.json/p1/canvas/1020/page",
          "type": "AnnotationPage",
          "items": [
            {
              "id": "https://amsterdamtimemachine.github.io/amsterdam-in-motion-750/iiif/kabouters-aktie-tegen-autos-en-uitlaatgassen.json/p1/canvas/1020/anno",
              "type": "Annotation",
              "motivation": "painting",
              "body": {
                "id": "https://service.archief.nl/iip/iipsrv?IIIF=/8a/94/e0/91/02/1d/4e/5b/85/38/bf/f0/46/8d/44/dc/c635cb35-23d0-4818-adba-4f45ddda7229.jp2/full/full/0/default.jpg",
                "type": "Image",
                "height": 2425,
                "width": 3703,
                "service": [
                  {
                    "@id": "https://service.archief.nl/iip/iipsrv?IIIF=/8a/94/e0/91/02/1d/4e/5b/85/38/bf/f0/46/8d/44/dc/c635cb35-23d0-4818-adba-4f45ddda7229.jp2",
                    "@type": "ImageService2",
                    "profile": "http://iiif.io/api/image/2/level1"
                  }
                ],
                "format": "image/jpeg"
              },
              "target": "https://amsterdamtimemachine.github.io/amsterdam-in-motion-750/iiif/kabouters-aktie-tegen-autos-en-uitlaatgassen.json/p1/canvas/1020"
            }
          ]
        }
      ]
    },
    {
      "id": "https://amsterdamtimemachine.github.io/amsterdam-in-motion-750/iiif/kabouters-aktie-tegen-autos-en-uitlaatgassen.json/p1/canvas/1021",
      "type": "Canvas",
      "label": {},
      "height": 2425,
      "width": 3688,
      "metadata": [
        {
          "label": {
            "nl": [
              "Naam"
            ]
          },
          "value": {
            "nl": [
              ""
            ]
          }
        },
        {
          "label": {
            "nl": [
              "Beschrijving"
            ]
          },
          "value": {
            "nl": [
              "Kabouters-guerilla-afdeling voert aktie tegen autos en uitlaatgassen in Amsterdam. in Leidsestraat. Demonstrant met politieagent"
            ]
          }
        },
        {
          "label": {
            "nl": [
              "Datum (begin)"
            ]
          },
          "value": {
            "nl": [
              "1970-04-07"
            ]
          }
        },
        {
          "label": {
            "nl": [
              "Datum (eind)"
            ]
          },
          "value": {
            "nl": [
              "1970-04-07"
            ]
          }
        },
        {
          "label": {
            "nl": [
              "Fotograaf"
            ]
          },
          "value": {
            "nl": [
              "Verhoeff, Bert / Anefo"
            ]
          }
        },
        {
          "label": {
            "nl": [
              "Archief"
            ]
          },
          "value": {
            "nl": [
              "Nationaal Archief"
            ]
          }
        },
        {
          "label": {
            "nl": [
              "URL"
            ]
          },
          "value": {
            "nl": [
              "http://hdl.handle.net/10648/ab931292-d0b4-102d-bcf8-003048976d84"
            ]
          }
        },
        {
          "label": {
            "nl": [
              "Locatie"
            ]
          },
          "value": {
            "nl": [
              ""
            ]
          }
        }
      ],
      "items": [
        {
          "id": "https://amsterdamtimemachine.github.io/amsterdam-in-motion-750/iiif/kabouters-aktie-tegen-autos-en-uitlaatgassen.json/p1/canvas/1021/page",
          "type": "AnnotationPage",
          "items": [
            {
              "id": "https://amsterdamtimemachine.github.io/amsterdam-in-motion-750/iiif/kabouters-aktie-tegen-autos-en-uitlaatgassen.json/p1/canvas/1021/anno",
              "type": "Annotation",
              "motivation": "painting",
              "body": {
                "id": "https://service.archief.nl/iip/iipsrv?IIIF=/c1/f0/27/19/da/2b/49/6a/af/d1/58/b6/2c/d6/bd/d1/5fda7e86-7a55-4ba0-9de3-49c01830fa8b.jp2/full/full/0/default.jpg",
                "type": "Image",
                "height": 2425,
                "width": 3688,
                "service": [
                  {
                    "@id": "https://service.archief.nl/iip/iipsrv?IIIF=/c1/f0/27/19/da/2b/49/6a/af/d1/58/b6/2c/d6/bd/d1/5fda7e86-7a55-4ba0-9de3-49c01830fa8b.jp2",
                    "@type": "ImageService2",
                    "profile": "http://iiif.io/api/image/2/level1"
                  }
                ],
                "format": "image/jpeg"
              },
              "target": "https://amsterdamtimemachine.github.io/amsterdam-in-motion-750/iiif/kabouters-aktie-tegen-autos-en-uitlaatgassen.json/p1/canvas/1021"
            }
          ]
        }
      ]
    },
    {
      "id": "https://amsterdamtimemachine.github.io/amsterdam-in-motion-750/iiif/kabouters-aktie-tegen-autos-en-uitlaatgassen.json/p1/canvas/1022",
      "type": "Canvas",
      "label": {},
      "height": 2425,
      "width": 3688,
      "metadata": [
        {
          "label": {
            "nl": [
              "Naam"
            ]
          },
          "value": {
            "nl": [
              ""
            ]
          }
        },
        {
          "label": {
            "nl": [
              "Beschrijving"
            ]
          },
          "value": {
            "nl": [
              "Kabouters-guerilla-afdeling voert aktie tegen autos en uitlaatgassen in Amsterdam. Jongelui blokkeren de rijweg met een Citroen 2CV (lelijke eend) op Prinsengracht tussen Leidsestraat en Leidsegracht."
            ]
          }
        },
        {
          "label": {
            "nl": [
              "Datum (begin)"
            ]
          },
          "value": {
            "nl": [
              "1970-04-07"
            ]
          }
        },
        {
          "label": {
            "nl": [
              "Datum (eind)"
            ]
          },
          "value": {
            "nl": [
              "1970-04-07"
            ]
          }
        },
        {
          "label": {
            "nl": [
              "Fotograaf"
            ]
          },
          "value": {
            "nl": [
              "Verhoeff, Bert / Anefo"
            ]
          }
        },
        {
          "label": {
            "nl": [
              "Archief"
            ]
          },
          "value": {
            "nl": [
              "Nationaal Archief"
            ]
          }
        },
        {
          "label": {
            "nl": [
              "URL"
            ]
          },
          "value": {
            "nl": [
              "http://hdl.handle.net/10648/ab930fd6-d0b4-102d-bcf8-003048976d84"
            ]
          }
        },
        {
          "label": {
            "nl": [
              "Locatie"
            ]
          },
          "value": {
            "nl": [
              ""
            ]
          }
        }
      ],
      "items": [
        {
          "id": "https://amsterdamtimemachine.github.io/amsterdam-in-motion-750/iiif/kabouters-aktie-tegen-autos-en-uitlaatgassen.json/p1/canvas/1022/page",
          "type": "AnnotationPage",
          "items": [
            {
              "id": "https://amsterdamtimemachine.github.io/amsterdam-in-motion-750/iiif/kabouters-aktie-tegen-autos-en-uitlaatgassen.json/p1/canvas/1022/anno",
              "type": "Annotation",
              "motivation": "painting",
              "body": {
                "id": "https://service.archief.nl/iip/iipsrv?IIIF=/32/69/1a/93/2e/e8/47/5f/96/c2/4f/cd/bb/77/8d/96/3704a396-2488-40c3-8ab1-98be496e6c7a.jp2/full/full/0/default.jpg",
                "type": "Image",
                "height": 2425,
                "width": 3688,
                "service": [
                  {
                    "@id": "https://service.archief.nl/iip/iipsrv?IIIF=/32/69/1a/93/2e/e8/47/5f/96/c2/4f/cd/bb/77/8d/96/3704a396-2488-40c3-8ab1-98be496e6c7a.jp2",
                    "@type": "ImageService2",
                    "profile": "http://iiif.io/api/image/2/level1"
                  }
                ],
                "format": "image/jpeg"
              },
              "target": "https://amsterdamtimemachine.github.io/amsterdam-in-motion-750/iiif/kabouters-aktie-tegen-autos-en-uitlaatgassen.json/p1/canvas/1022"
            }
          ]
        }
      ]
    },
    {
      "id": "https://amsterdamtimemachine.github.io/amsterdam-in-motion-750/iiif/kabouters-aktie-tegen-autos-en-uitlaatgassen.json/p1/canvas/1023",
      "type": "Canvas",
      "label": {},
      "height": 2425,
      "width": 3703,
      "metadata": [
        {
          "label": {
            "nl": [
              "Naam"
            ]
          },
          "value": {
            "nl": [
              ""
            ]
          }
        },
        {
          "label": {
            "nl": [
              "Beschrijving"
            ]
          },
          "value": {
            "nl": [
              "Kabouters-guerilla-afdeling voert aktie tegen autos en uitlaatgassen in Amsterdam. Jongelui gaan op rijweg zitten in Leidsestraat, politieagent komt aanlopen"
            ]
          }
        },
        {
          "label": {
            "nl": [
              "Datum (begin)"
            ]
          },
          "value": {
            "nl": [
              "1970-04-07"
            ]
          }
        },
        {
          "label": {
            "nl": [
              "Datum (eind)"
            ]
          },
          "value": {
            "nl": [
              "1970-04-07"
            ]
          }
        },
        {
          "label": {
            "nl": [
              "Fotograaf"
            ]
          },
          "value": {
            "nl": [
              "Verhoeff, Bert / Anefo"
            ]
          }
        },
        {
          "label": {
            "nl": [
              "Archief"
            ]
          },
          "value": {
            "nl": [
              "Nationaal Archief"
            ]
          }
        },
        {
          "label": {
            "nl": [
              "URL"
            ]
          },
          "value": {
            "nl": [
              "http://hdl.handle.net/10648/ab930f18-d0b4-102d-bcf8-003048976d84"
            ]
          }
        },
        {
          "label": {
            "nl": [
              "Locatie"
            ]
          },
          "value": {
            "nl": [
              ""
            ]
          }
        }
      ],
      "items": [
        {
          "id": "https://amsterdamtimemachine.github.io/amsterdam-in-motion-750/iiif/kabouters-aktie-tegen-autos-en-uitlaatgassen.json/p1/canvas/1023/page",
          "type": "AnnotationPage",
          "items": [
            {
              "id": "https://amsterdamtimemachine.github.io/amsterdam-in-motion-750/iiif/kabouters-aktie-tegen-autos-en-uitlaatgassen.json/p1/canvas/1023/anno",
              "type": "Annotation",
              "motivation": "painting",
              "body": {
                "id": "https://service.archief.nl/iip/iipsrv?IIIF=/5f/54/f5/55/7b/4b/47/22/9e/f2/3a/56/a0/a0/b5/92/d4efa2ed-f795-4790-82d6-75fce96e5d2d.jp2/full/full/0/default.jpg",
                "type": "Image",
                "height": 2425,
                "width": 3703,
                "service": [
                  {
                    "@id": "https://service.archief.nl/iip/iipsrv?IIIF=/5f/54/f5/55/7b/4b/47/22/9e/f2/3a/56/a0/a0/b5/92/d4efa2ed-f795-4790-82d6-75fce96e5d2d.jp2",
                    "@type": "ImageService2",
                    "profile": "http://iiif.io/api/image/2/level1"
                  }
                ],
                "format": "image/jpeg"
              },
              "target": "https://amsterdamtimemachine.github.io/amsterdam-in-motion-750/iiif/kabouters-aktie-tegen-autos-en-uitlaatgassen.json/p1/canvas/1023"
            }
          ]
        }
      ]
    }
  ],
  "seeAlso": [
    {
      "@type": "schema:Event",
      "schema:name": "Kabouters-aktie tegen autos en uitlaatgassen",
      "schema:description": "",
      "schema:startDate": {
        "@type": "xsd:date",
        "@value": "1970-04-07"
      },
      "schema:endDate": {
        "@type": "xsd:date",
        "@value": "1970-04-07"
      },
      "schema:location": [
        {
          "@type": "schema:Place",
          "schema:name": ""
        }
      ],
      "schema:additionalType": [
        {
          "@id": "https://digitaalerfgoed.poolparty.biz/atm/42d4c3eb-08e3-4b9a-8c8a-a124ae114bab",
          "@type": "skos:Concept",
          "skos:prefLabel": {
            "@language": "nl",
            "@value": "Demonstraties"
          }
        },
        {
          "@id": "https://digitaalerfgoed.poolparty.biz/atm/a3c22faf-7d0a-4476-b6fc-1969d56481a3",
          "@type": "skos:Concept",
          "skos:prefLabel": {
            "@language": "nl",
            "@value": "Klimaat"
          }
        },
        {
          "@id": "https://digitaalerfgoed.poolparty.biz/atm/08f07179-519a-47c2-8f76-3938ac63e53f",
          "@type": "skos:Concept",
          "skos:prefLabel": {
            "@language": "nl",
            "@value": "Mobiliteit"
          }
        }
      ]
    }
  ]
}